import_export_stomp/__init__.py
import_export_stomp/admin.py
import_export_stomp/admin_actions.py
import_export_stomp/apps.py
import_export_stomp/fields.py
import_export_stomp/locale/eu/LC_MESSAGES/django.po
import_export_stomp/locale/pt/LC_MESSAGES/django.mo
import_export_stomp/locale/pt/LC_MESSAGES/django.po
import_export_stomp/management/__init__.py
import_export_stomp/management/commands/__init__.py
import_export_stomp/management/commands/import_export_pubsub.py
import_export_stomp/migrations/0001_initial.py
import_export_stomp/migrations/0002_auto_20190923_1132.py
import_export_stomp/migrations/0003_exportjob.py
import_export_stomp/migrations/0004_exportjob_email_on_completion.py
import_export_stomp/migrations/0005_exportjob_site_of_origin.py
import_export_stomp/migrations/0006_auto_20191125_1236.py
import_export_stomp/migrations/0007_auto_20210210_1831.py
import_export_stomp/migrations/0008_alter_exportjob_id_alter_importjob_id.py
import_export_stomp/migrations/0009_alter_exportjob_options_alter_importjob_options_and_more.py
import_export_stomp/migrations/0010_remove_exportjob_email_on_completion_and_more.py
import_export_stomp/migrations/0011_alter_exportjob_id_alter_importjob_id.py
import_export_stomp/migrations/__init__.py
import_export_stomp/models/__init__.py
import_export_stomp/models/exportjob.py
import_export_stomp/models/importjob.py
import_export_stomp/pubsub.py
import_export_stomp/resources.py
import_export_stomp/tasks.py
import_export_stomp/templates/email/export_job_completion.html
import_export_stomp/templates/widgets/signed_url_file.html
import_export_stomp/templatetags/__init__.py
import_export_stomp/templatetags/settings.py
import_export_stomp/urls.py
import_export_stomp/utils.py
import_export_stomp/views.py
import_export_stomp/widgets.py
django_import_export_stomp-0.4.0.dist-info/LICENSE
django_import_export_stomp-0.4.0.dist-info/METADATA
django_import_export_stomp-0.4.0.dist-info/WHEEL
django_import_export_stomp-0.4.0.dist-info/RECORD
