Metadata-Version: 2.1
Name: django-import-export-stomp
Version: 0.4.0
Summary: Run django-import-export processes using django-stomp
License: MIT
Author: Nilton Frederico Teixeira
Author-email: 9078708+niltonfrederico@users.noreply.github.com
Requires-Python: >=3.10,<4.0
Classifier: License :: OSI Approved :: MIT License
Classifier: Programming Language :: Python :: 3
Classifier: Programming Language :: Python :: 3.10
Classifier: Programming Language :: Python :: 3.11
Requires-Dist: django (>=5.1)
Requires-Dist: django-author
Requires-Dist: django-import-export
Requires-Dist: django-stomp
Requires-Dist: tablib[html,ods,xls,xlsx,yaml]
